cookiecutter_practice/FoliumMap.py
cookiecutter_practice/LeafMap.py
cookiecutter_practice/__init__.py
cookiecutter_practice/common.py
cookiecutter_practice/cookiecutter_practice.py
cookiecutter_practice-4.0.0.dist-info/licenses/LICENSE
cookiecutter_practice-4.0.0.dist-info/METADATA
cookiecutter_practice-4.0.0.dist-info/WHEEL
cookiecutter_practice-4.0.0.dist-info/entry_points.txt
cookiecutter_practice-4.0.0.dist-info/top_level.txt
cookiecutter_practice-4.0.0.dist-info/RECORD
