Metadata-Version: 2.4
Name: cookiecutter-practice
Version: 4.0.0
Summary: Python Boilerplate contains all the boilerplate you need to create a Python package.
Author-email: Martin Arrogante <arrogantemartin@gmail.com>
License: MIT License
Project-URL: Homepage, https://github.com/marts-dev/cookiecutter-practice
Keywords: cookiecutter-practice
Classifier: Intended Audience :: Developers
Classifier: License :: OSI Approved :: MIT License
Classifier: Natural Language :: English
Classifier: Programming Language :: Python :: 3.8
Classifier: Programming Language :: Python :: 3.9
Classifier: Programming Language :: Python :: 3.10
Classifier: Programming Language :: Python :: 3.11
Classifier: Programming Language :: Python :: 3.12
Requires-Python: >=3.8
License-File: LICENSE
Requires-Dist: numpy
Requires-Dist: ipyleaflet
Requires-Dist: folium
Requires-Dist: geopandas
Requires-Dist: rasterio
Requires-Dist: fiona
Requires-Dist: matplotlib
Requires-Dist: localtileserver
Requires-Dist: ipywidgets
Provides-Extra: all
Requires-Dist: cookiecutter-practice[extra]; extra == "all"
Provides-Extra: extra
Requires-Dist: pandas; extra == "extra"
Dynamic: license-file
